liteboty_stream/__init__.py
liteboty_stream/cli.py
liteboty_stream/liteboty_stream.py
liteboty_stream/liteboty_stream_ui.py
liteboty_stream/redis_subscriber.py
liteboty_stream-0.2.1.dist-info/entry_points.txt
liteboty_stream-0.2.1.dist-info/METADATA
liteboty_stream-0.2.1.dist-info/WHEEL
liteboty_stream-0.2.1.dist-info/RECORD
